code_owners/__init__.py
code_owners/config.py
code_owners/parser.py
pbx_code_owners-1.2.0.dist-info/METADATA
pbx_code_owners-1.2.0.dist-info/WHEEL
pbx_code_owners-1.2.0.dist-info/entry_points.txt
pbx_code_owners-1.2.0.dist-info/top_level.txt
pbx_code_owners-1.2.0.dist-info/RECORD
