Metadata-Version: 2.1
Name: pbx-code-owners
Version: 1.2.0
Summary: Code Owners implementation
Home-page: https://getprintbox.com/
Author: 
Author-email: 
Requires-Python: >=3.8
Requires-Dist: pyyaml
Requires-Dist: requests
